[
  {
    "id": "843fad62-42c2-42f0-aba8-06815dd91787",
    "_version": 1,
    "hrid": "it00000000030",
    "holdingsRecordId": "186c6491-fa13-4c6e-b9f1-ca1b90da7ec9",
    "formerIds": [],
    "discoverySuppress": null,
    "title": "test-instance-3",
    "contributorNames": [],
    "callNumber": null,
    "barcode": "8381",
    "effectiveShelvingOrder": null,
    "accessionNumber": null,
    "itemLevelCallNumber": null,
    "itemLevelCallNumberPrefix": null,
    "itemLevelCallNumberSuffix": null,
    "itemLevelCallNumberTypeId": null,
    "effectiveCallNumberComponents": {
      "callNumber": null,
      "prefix": null,
      "suffix": null,
      "typeId": null
    },
    "volume": null,
    "enumeration": null,
    "chronology": null,
    "yearCaption": [],
    "itemIdentifier": null,
    "copyNumber": null,
    "numberOfPieces": null,
    "descriptionOfPieces": null,
    "numberOfMissingPieces": null,
    "missingPieces": null,
    "missingPiecesDate": null,
    "itemDamagedStatusId": null,
    "itemDamagedStatusDate": null,
    "administrativeNotes": [],
    "notes": [],
    "circulationNotes": [],
    "status": {
      "name": "Available",
      "date": 1653885393842
    },
    "materialType": {
      "id": "1a54b431-2e4f-452d-9cae-9cee66c9a892",
      "name": "book"
    },
    "isBoundWith": false,
    "boundWithTitles": null,
    "permanentLoanType": {
      "id": "2b94c631-fca9-4892-a730-03ee529ffe27",
      "name": "Can circulate"
    },
    "temporaryLoanType": null,
    "permanentLocation": null,
    "temporaryLocation": null,
    "effectiveLocation": {
      "id": "fcd64ce1-6995-48f0-840e-89ffa2288371",
      "name": "Main Library"
    },
    "electronicAccess": [],
    "inTransitDestinationServicePointId": null,
    "statisticalCodeIds": [],
    "purchaseOrderLineIdentifier": null,
    "metadata": {
      "createdDate": 1653885393841,
      "createdByUserId": "d4f06afe-57bf-4654-9cc1-920630105002",
      "createdByUsername": null,
      "updatedDate": 1653885393841,
      "updatedByUserId": "d4f06afe-57bf-4654-9cc1-920630105002",
      "updatedByUsername": null
    },
    "tags": {
      "tagList": []
    },
    "lastCheckIn": null
  },
  {
    "id": "58318c1f-9235-4664-b5ae-51254c248a02",
    "_version": 1,
    "hrid": "it00000000031",
    "holdingsRecordId": "186c6491-fa13-4c6e-b9f1-ca1b90da7ec9",
    "formerIds": [],
    "discoverySuppress": null,
    "title": "test-instance-3",
    "contributorNames": [],
    "callNumber": null,
    "barcode": "3839",
    "effectiveShelvingOrder": null,
    "accessionNumber": null,
    "itemLevelCallNumber": null,
    "itemLevelCallNumberPrefix": null,
    "itemLevelCallNumberSuffix": null,
    "itemLevelCallNumberTypeId": null,
    "effectiveCallNumberComponents": {
      "callNumber": null,
      "prefix": null,
      "suffix": null,
      "typeId": null
    },
    "volume": null,
    "enumeration": null,
    "chronology": null,
    "yearCaption": [],
    "itemIdentifier": null,
    "copyNumber": null,
    "numberOfPieces": null,
    "descriptionOfPieces": null,
    "numberOfMissingPieces": null,
    "missingPieces": null,
    "missingPiecesDate": null,
    "itemDamagedStatusId": null,
    "itemDamagedStatusDate": null,
    "administrativeNotes": [],
    "notes": [],
    "circulationNotes": [],
    "status": {
      "name": "Available",
      "date": 1653885395015
    },
    "materialType": {
      "id": "1a54b431-2e4f-452d-9cae-9cee66c9a892",
      "name": "book"
    },
    "isBoundWith": false,
    "boundWithTitles": null,
    "permanentLoanType": {
      "id": "2b94c631-fca9-4892-a730-03ee529ffe27",
      "name": "Can circulate"
    },
    "temporaryLoanType": null,
    "permanentLocation": null,
    "temporaryLocation": null,
    "effectiveLocation": {
      "id": "fcd64ce1-6995-48f0-840e-89ffa2288371",
      "name": "Main Library"
    },
    "electronicAccess": [],
    "inTransitDestinationServicePointId": null,
    "statisticalCodeIds": [],
    "purchaseOrderLineIdentifier": null,
    "metadata": {
      "createdDate": 1653885395015,
      "createdByUserId": "d4f06afe-57bf-4654-9cc1-920630105002",
      "createdByUsername": null,
      "updatedDate": 1653885395015,
      "updatedByUserId": "d4f06afe-57bf-4654-9cc1-920630105002",
      "updatedByUsername": null
    },
    "tags": {
      "tagList": []
    },
    "lastCheckIn": null
  }
]